pass_totp/__init__.py
pass_totp/cli.py
pass_totp-1.0.dist-info/DESCRIPTION.rst
pass_totp-1.0.dist-info/METADATA
pass_totp-1.0.dist-info/RECORD
pass_totp-1.0.dist-info/WHEEL
pass_totp-1.0.dist-info/entry_points.txt
pass_totp-1.0.dist-info/metadata.json
pass_totp-1.0.dist-info/top_level.txt
