Metadata-Version: 2.0
Name: pass-totp
Version: 1.0
Summary: UNKNOWN
Home-page: https://gitlab.com/jgelens/pass-totp
Author: Jeffrey Gelens
Author-email: jeffrey@noppo.pro
License: Apache 2
Keywords: totp,passwordstore,extension
Platform: UNKNOWN
Classifier: Programming Language :: Python
Classifier: Programming Language :: Python :: 3.6
Classifier: License :: OSI Approved :: Apache Software License
Classifier: Environment :: Console
Requires-Dist: click (==6.7)
Requires-Dist: click-completion (==0.2.1)
Requires-Dist: jinja2 (==2.9.6)
Requires-Dist: markupsafe (==1.0)
Requires-Dist: passlib (==1.7.1)
Requires-Dist: pyperclip (==1.5.27)
Requires-Dist: six (==1.11.0)
